lru_cache_pubsub_cache_clear/__init__.py
lru_cache_pubsub_cache_clear/decorators.py
lru_cache_pubsub_cache_clear-0.0.9.dist-info/LICENSE
lru_cache_pubsub_cache_clear-0.0.9.dist-info/METADATA
lru_cache_pubsub_cache_clear-0.0.9.dist-info/WHEEL
lru_cache_pubsub_cache_clear-0.0.9.dist-info/top_level.txt
lru_cache_pubsub_cache_clear-0.0.9.dist-info/RECORD
