Metadata-Version: 2.1
Name: lru-cache-pubsub-cache-clear
Version: 0.0.9
Summary: redis based cache_clear() for lru_cache
Home-page: https://github.com/pglotov/lru_cache_pubsub_cache_clear
Author: Petr Glotov
Author-email: pglotov@yahoo.com
License: UNKNOWN
Platform: UNKNOWN
Classifier: Programming Language :: Python :: 2
Classifier: Programming Language :: Python :: 3
Classifier: License :: OSI Approved :: MIT License
Classifier: Operating System :: OS Independent
